pww_scripts/__init__.py
pww_scripts/main.py
pww_scripts/entity/Artist.py
pww_scripts/entity/Backtrack.py
pww_scripts/entity/Info.py
pww_scripts/entity/Log.py
pww_scripts/entity/MySQLConnection.py
pww_scripts/entity/Pot.py
pww_scripts/entity/__init__.py
pww_scripts/init/__init__.py
pww_scripts/init/parameter.py
pww_scripts/script/__init__.py
pww_scripts/script/get_info_and_save.py
pww_scripts/script/get_pot_info_and_save.py
pww_scripts/script/insert_spider_data.py
pww_scripts/script/kemono_transform.py
pww_scripts/utils/__init__.py
tool_scripts-0.2.1.dist-info/METADATA
tool_scripts-0.2.1.dist-info/WHEEL
tool_scripts-0.2.1.dist-info/top_level.txt
tool_scripts-0.2.1.dist-info/RECORD
