Metadata-Version: 2.1
Name: tool_scripts
Version: 0.2.1
Summary: 自制各种脚本
Author: pww
Author-email: 2118969873pww@gmail.com
Classifier: Programming Language :: Python :: 3
Classifier: License :: OSI Approved :: MIT License
Classifier: Operating System :: OS Independent
Requires-Python: >=3.12
